{
    "head_word": "אֹ֫הֶל", 
    "pos": "noun masculine", 
    "primary": "tent", 
    "description": "the sacred tent used in worship of God", 
    "senses": [
        {
            "number": 1, 
            "primary": null, 
            "description": null
        }, 
        {
            "number": 2, 
            "primary": null, 
            "description": null
        }, 
        {
            "number": 3, 
            "primary": null, 
            "description": "the sacred tent used in worship of God"
        }
    ]
}