{
    "head_word": "גָּרַע", 
    "pos": "verb", 
    "primary": "diminish, restrain, withdraw", 
    "description": null, 
    "senses": [
        {
            "number": 1, 
            "primary": null, 
            "description": null
        }, 
        {
            "number": 2, 
            "primary": null, 
            "description": null
        }, 
        {
            "number": 3, 
            "primary": null, 
            "description": null
        }, 
        {
            "number": 4, 
            "primary": null, 
            "description": null
        }, 
        {
            "number": 5, 
            "primary": null, 
            "description": null
        }
    ]
}