{
    "head_word": "בֶּ֫לַע", 
    "pos": "proper name, masculine", 
    "primary": null, 
    "description": "a king\n    of Edom", 
    "senses": [
        {
            "number": 1, 
            "primary": null, 
            "description": "a king\n    of Edom"
        }, 
        {
            "number": 2, 
            "primary": null, 
            "description": "1st son of Benjamin"
        }, 
        {
            "number": 3, 
            "primary": null, 
            "description": "a Reubenite"
        }
    ]
}