{
    "head_word": "יְעוּאֵל", 
    "pos": "proper name, masculine", 
    "primary": null, 
    "description": "יְעוּאֵל son of Zerah", 
    "senses": [
        {
            "number": 1, 
            "primary": null, 
            "description": "יְעוּאֵל son of Zerah"
        }, 
        {
            "number": 2, 
            "primary": null, 
            "description": "יְעִיאֵל: \na. a companion of Ezra Ezra 8:13, \n\nᵐ5\n\nL\n\n\nΙειηλ.\n    \n\nb. a chief of the Reubenites 1Chr 5:7, \n\nᵐ5\n\n\nΙωηλ.\n    \n\nc. Levites, \n\nᵐ5\n\n\nΙωηλ, Ιειηλ, etc.: (I) 1Chr 15:18; 1Chr 15:21; 1Chr 16:5 (twice in verse); 2Chr 20:14 (2) 2Chr 35:9.\n    \n\nd.\none of those who took strange wives Ezra 10:43, \n\nᵐ5\n\n\nΙαηλ, Ιειηλ, etc."
        }, 
        {
            "number": 3, 
            "primary": null, 
            "description": "יעואל\n\nKt\n, יְעִיאֵל\n\nQr"
        }
    ]
}