{
    "head_word": "מַעֲכָה", 
    "pos": "proper name, masculine, feminine [also of a people]", 
    "primary": null, 
    "description": "son of\n        Nahor by his concubine", 
    "senses": [
        {
            "number": 1, 
            "primary": null, 
            "description": "son of\n        Nahor by his concubine"
        }, 
        {
            "number": 2, 
            "primary": null, 
            "description": "Geshurite princess,\n        wife\n        of David, mother of Absalom"
        }, 
        {
            "number": 3, 
            "primary": null, 
            "description": "of a people"
        }
    ]
}