{
    "head_word": "רַךְ", 
    "pos": "adjective", 
    "primary": "tender, delicate, soft", 
    "description": "weak of heart, timid", 
    "senses": [
        {
            "number": 1, 
            "primary": null, 
            "description": null
        }, 
        {
            "number": 2, 
            "primary": null, 
            "description": "weak of heart, timid"
        }, 
        {
            "number": 3, 
            "primary": null, 
            "description": null
        }
    ]
}